{
  "custom": true,
  "options": {
    "electra": "electra-one-a-port-2",
    "electraOneCtrl": "electra-one-a-ctrl",
    "scenario": "default",
    "clock": "bacara",
    "transpose": "bacara",
    "transposeChannel": 15,
    "general": null,
    "generalChannel": 1,
    "remote": null,
    "remoteChannel": 1,
    "bank": 0,
    "slot": 0,
    "id": 0,
    "name": ""
  },
  "electra": {
    "checkPresetVia": "none"
  },
  "midi": {
    "ports": {
      "electra-one-a-port-1": {
        "darwin": "Electra Controller A Electra Port 1"
      },
      "electra-one-a-port-2": {
        "darwin": "Electra Controller A Electra Port 2"
      },
      "electra-one-a-ctrl": {
        "darwin": "Electra Controller A Electra CTRL"
      },
      "electra-one-b-port-1": {
        "darwin": "Electra Controller B Electra Port 1"
      },
      "electra-one-b-port-2": {
        "darwin": "Electra Controller B Electra Port 2"
      },
      "electra-one-b-ctrl": {
        "darwin": "Electra Controller B Electra CTRL"
      }
    }
  },
  "preset": {
    "midi": {
      "ports": {
        "input": [
          {
            "name": "Midihub MH-3Q5WJAZ Port 1",
            "short": "Midihub MH-3.1"
          },
          {
            "name": "Midihub MH-3Q5WJAZ Port 2",
            "short": "Midihub MH-3.2"
          },
          {
            "name": "Midihub MH-3Q5WJAZ Port 3",
            "short": "Midihub MH-3.3"
          },
          {
            "name": "Midihub MH-3Q5WJAZ Port 4",
            "short": "Midihub MH-3.4"
          },
          {
            "name": "Akai APC40",
            "short": "Akai APC.40"
          },
          {
            "name": "MX-1",
            "short": "MX-.1"
          },
          {
            "name": "MX-1 CTRL",
            "short": "MX-1.CTRL"
          },
          {
            "name": "MX-1 USB1",
            "short": "MX-1 USB.1"
          },
          {
            "name": "MX-1 USB1 CTRL",
            "short": "MX-1 USB1.CTRL"
          },
          {
            "name": "MX-1 USB2",
            "short": "MX-1 USB.2"
          },
          {
            "name": "MX-1 USB2 CTRL",
            "short": "MX-1 USB2.CTRL"
          },
          {
            "name": "MX-1 USB3",
            "short": "MX-1 USB.3"
          },
          {
            "name": "MX-1 USB3 CTRL",
            "short": "MX-1 USB3.CTRL"
          },
          {
            "name": "MX-1 USB4",
            "short": "MX-1 USB.4"
          },
          {
            "name": "MX-1 USB4 CTRL",
            "short": "MX-1 USB4.CTRL"
          },
          {
            "name": "Touch Block Bluetooth",
            "short": "Touch Block Bl"
          },
          {
            "name": "Lightpad BLOCK ",
            "short": "Lightpad BLOCK"
          },
          {
            "name": "Electra Controller A Electra Port 1",
            "short": "Electra Cont A.1",
            "device": "electra-one-a-port-1"
          },
          {
            "name": "Electra Controller A Electra Port 2",
            "short": "Electra Cont A.2",
            "device": "electra-one-a-port-2"
          },
          {
            "name": "Electra Controller A Electra CTRL",
            "short": "Electra Contro A.CTRL",
            "device": "electra-one-a-ctrl"
          },
          {
            "name": "MRCC Port 1",
            "short": "MRCC Port.1"
          },
          {
            "name": "MRCC Port 2",
            "short": "MRCC Port.2"
          },
          {
            "name": "MRCC Port 3",
            "short": "MRCC Port.3"
          },
          {
            "name": "MRCC Port 4",
            "short": "MRCC Port.4"
          },
          {
            "name": "MRCC Port 5",
            "short": "MRCC Port.5"
          },
          {
            "name": "MRCC Port 6",
            "short": "MRCC Port.6"
          },
          {
            "name": "MRCC Port 7",
            "short": "MRCC Port.7"
          },
          {
            "name": "MRCC Port 8",
            "short": "MRCC Port.8"
          },
          {
            "name": "MRCC Port 9",
            "short": "MRCC Port.9"
          },
          {
            "name": "MRCC Port 10",
            "short": "MRCC Port.10"
          },
          {
            "name": "MRCC Port 11",
            "short": "MRCC Port.11"
          },
          {
            "name": "MRCC Port 12",
            "short": "MRCC Port.12"
          },
          {
            "name": "MRCC Port 13",
            "short": "MRCC Port.13"
          },
          {
            "name": "MRCC Port 14",
            "short": "MRCC Port.14"
          },
          {
            "name": "MRCC Port 15",
            "short": "MRCC Port.15"
          },
          {
            "name": "MRCC Port 16",
            "short": "MRCC Port.16"
          },
          {
            "name": "Bacara",
            "short": "Bacara",
            "device": "bacara"
          }
        ],
        "output": [
          {
            "name": "Midihub MH-3Q5WJAZ Port 1",
            "short": "Midihub MH-3.1"
          },
          {
            "name": "Midihub MH-3Q5WJAZ Port 2",
            "short": "Midihub MH-3.2"
          },
          {
            "name": "Midihub MH-3Q5WJAZ Port 3",
            "short": "Midihub MH-3.3"
          },
          {
            "name": "Midihub MH-3Q5WJAZ Port 4",
            "short": "Midihub MH-3.4"
          },
          {
            "name": "Akai APC40",
            "short": "Akai APC.40"
          },
          {
            "name": "MX-1",
            "short": "MX-.1"
          },
          {
            "name": "MX-1 CTRL",
            "short": "MX-1.CTRL"
          },
          {
            "name": "MX-1 USB1",
            "short": "MX-1 USB.1"
          },
          {
            "name": "MX-1 USB1 CTRL",
            "short": "MX-1 USB1.CTRL"
          },
          {
            "name": "MX-1 USB2",
            "short": "MX-1 USB.2"
          },
          {
            "name": "MX-1 USB2 CTRL",
            "short": "MX-1 USB2.CTRL"
          },
          {
            "name": "MX-1 USB3",
            "short": "MX-1 USB.3"
          },
          {
            "name": "MX-1 USB3 CTRL",
            "short": "MX-1 USB3.CTRL"
          },
          {
            "name": "MX-1 USB4",
            "short": "MX-1 USB.4"
          },
          {
            "name": "MX-1 USB4 CTRL",
            "short": "MX-1 USB4.CTRL"
          },
          {
            "name": "Touch Block Bluetooth",
            "short": "Touch Block Bl"
          },
          {
            "name": "Lightpad BLOCK ",
            "short": "Lightpad BLOCK"
          },
          {
            "name": "Electra Controller A Electra Port 1",
            "short": "Electra Cont A.1",
            "device": "electra-one-a-port-1"
          },
          {
            "name": "Electra Controller A Electra Port 2",
            "short": "Electra Cont A.2",
            "device": "electra-one-a-port-2"
          },
          {
            "name": "Electra Controller A Electra CTRL",
            "short": "Electra Contro A.CTRL",
            "device": "electra-one-a-ctrl"
          },
          {
            "name": "MRCC Port 1",
            "short": "MRCC Port.1"
          },
          {
            "name": "MRCC Port 2",
            "short": "MRCC Port.2"
          },
          {
            "name": "MRCC Port 3",
            "short": "MRCC Port.3"
          },
          {
            "name": "MRCC Port 4",
            "short": "MRCC Port.4"
          },
          {
            "name": "MRCC Port 5",
            "short": "MRCC Port.5"
          },
          {
            "name": "MRCC Port 6",
            "short": "MRCC Port.6"
          },
          {
            "name": "MRCC Port 7",
            "short": "MRCC Port.7"
          },
          {
            "name": "MRCC Port 8",
            "short": "MRCC Port.8"
          },
          {
            "name": "MRCC Port 9",
            "short": "MRCC Port.9"
          },
          {
            "name": "MRCC Port 10",
            "short": "MRCC Port.10"
          },
          {
            "name": "MRCC Port 11",
            "short": "MRCC Port.11"
          },
          {
            "name": "MRCC Port 12",
            "short": "MRCC Port.12"
          },
          {
            "name": "MRCC Port 13",
            "short": "MRCC Port.13"
          },
          {
            "name": "MRCC Port 14",
            "short": "MRCC Port.14"
          },
          {
            "name": "MRCC Port 15",
            "short": "MRCC Port.15"
          },
          {
            "name": "MRCC Port 16",
            "short": "MRCC Port.16"
          },
          {
            "name": "Bacara",
            "short": "Bacara",
            "device": "bacara"
          }
        ]
      }
    }
  }
}
